Metadata-Version: 2.4
Name: imageprocessing-edlopeskk
Version: 0.0.1
Summary: My short description
Home-page: https://github.com/edlopes07/image-processing-package.git
Author: Eduardo
Author-email: edulopes.alves07@gmail.com
Requires-Python: >=3.8
Requires-Dist: matplotlib
Requires-Dist: numpy
Requires-Dist: scikit-image>=0.16.1
Dynamic: author
Dynamic: author-email
Dynamic: description
Dynamic: description-content-type
Dynamic: home-page
Dynamic: requires-dist
Dynamic: requires-python
Dynamic: summary
